<?xml version="1.0" encoding="UTF-8"?>
<repomd xmlns="http://linux.duke.edu/metadata/repo">
  <data type="other">
    <location href="repodata/other.xml.gz"/>
    <checksum type="sha">ebf79ad1c84f74c04bf6656f9ae35ec2d10570be</checksum>
    <timestamp>1380350694</timestamp>
    <open-checksum type="sha">1657aac989c8f14b4949dbdd60db3c26ac331c69</open-checksum>
  </data>
  <data type="filelists">
    <location href="repodata/filelists.xml.gz"/>
    <checksum type="sha">af9fb23ff6e1a3bd438ea4f754c2ce453f708890</checksum>
    <timestamp>1380350694</timestamp>
    <open-checksum type="sha">2caf748d24ed993cc9404a5e958688ed40c9f719</open-checksum>
  </data>
  <data type="primary">
    <location href="repodata/primary.xml.gz"/>
    <checksum type="sha">cbed3596988e822ba9e5fab1146df583f1f6b48c</checksum>
    <timestamp>1380350694</timestamp>
    <open-checksum type="sha">c3946df028dbfc832f66fa3e03dbe82248d5c91a</open-checksum>
  </data>
</repomd>
