<?xml version="1.0" encoding="UTF-8"?>
<repomd xmlns="http://linux.duke.edu/metadata/repo" xmlns:rpm="http://linux.duke.edu/metadata/rpm">
 <revision>1415536007</revision>
<data type="filelists">
  <checksum type="sha256">ebf5456f6d9b93be61ddd0cdc7181c6d47c3c9f1ca27e2130f14dce718b654cf</checksum>
  <open-checksum type="sha256">644d565118d39f3eac526a61c78510cd7d23c00459e8bb0e70400014058bd559</open-checksum>
  <location href="repodata/filelists.xml.gz"/>
  <timestamp>1415536008</timestamp>
  <size>50535</size>
  <open-size>895602</open-size>
</data>
<data type="other">
  <checksum type="sha256">abcf4866dff119a3daca29dbcaf47bc639e63c0c369a6ff266fce9f60449b204</checksum>
  <open-checksum type="sha256">aacbdcb3767b4c975afae000d6bc10868d551a12587b4b90ab8e10b7026e7edb</open-checksum>
  <location href="repodata/other.xml.gz"/>
  <timestamp>1415536008</timestamp>
  <size>3629</size>
  <open-size>16020</open-size>
</data>
<data type="primary">
  <checksum type="sha256">0d3ca587ce03495cd7cdfec4113cebf947510595698d5da38b48810e49871864</checksum>
  <open-checksum type="sha256">8e10ceeaee5aac0e3776b4015dd1c753263963ff1c1d157eb9c7381f7e693145</open-checksum>
  <location href="repodata/primary.xml.gz"/>
  <timestamp>1415536008</timestamp>
  <size>6527</size>
  <open-size>25141</open-size>
</data>
</repomd>
