<?xml version="1.0" encoding="UTF-8"?>
<repomd xmlns="http://linux.duke.edu/metadata/repo">
  <data type="other">
    <location href="repodata/other.xml.gz"/>
    <checksum type="sha">891074791e775891bc39121a119897b64709ecc3</checksum>
    <timestamp>1249877729</timestamp>
    <open-checksum type="sha">2165250b246efbb448d6f5c21a847b16a1372b4c</open-checksum>
  </data>
  <data type="filelists">
    <location href="repodata/filelists.xml.gz"/>
    <checksum type="sha">869b5a80596e4e44a1b6e2a2bcbea42ab8ee346c</checksum>
    <timestamp>1249877729</timestamp>
    <open-checksum type="sha">5103a481654e47bb6e9f4427889b5d4f4c5c8adf</open-checksum>
  </data>
  <data type="primary">
    <location href="repodata/primary.xml.gz"/>
    <checksum type="sha">938254c46b4d18f5c0c6001601a53f29e1fe6266</checksum>
    <timestamp>1249877729</timestamp>
    <open-checksum type="sha">ee603be1ae4f8e2eab152c4864ccebde1dd48d59</open-checksum>
  </data>
</repomd>
