<?xml version="1.0" encoding="UTF-8"?>
<repomd xmlns="http://linux.duke.edu/metadata/repo">
  <data type="other">
    <location href="repodata/other.xml.gz"/>
    <checksum type="sha">0681a8e54576ccfd945b086095134324cfdc7d2e</checksum>
    <timestamp>1305702913</timestamp>
    <open-checksum type="sha">dea7b5dda659e477f5aa6ca0638d8f9fc53504e1</open-checksum>
  </data>
  <data type="filelists">
    <location href="repodata/filelists.xml.gz"/>
    <checksum type="sha">f2b9ba490f729209cec8bd9c54e4201175a30011</checksum>
    <timestamp>1305702913</timestamp>
    <open-checksum type="sha">6d4f6b8317c514ede33710089ea7cdc89218757a</open-checksum>
  </data>
  <data type="primary">
    <location href="repodata/primary.xml.gz"/>
    <checksum type="sha">678fa9fbfed53ba2e03b6bc35df814706f5dbb99</checksum>
    <timestamp>1305702913</timestamp>
    <open-checksum type="sha">870e719cc2f32ab58012e24dc8c304749021c1b2</open-checksum>
  </data>
</repomd>
