<?xml version="1.0" encoding="UTF-8"?>
<repomd xmlns="http://linux.duke.edu/metadata/repo">
  <data type="other">
    <location href="repodata/other.xml.gz"/>
    <checksum type="sha">de8d9d3b014e687ed979a47680502d2012ed23bd</checksum>
    <timestamp>1253090753</timestamp>
    <open-checksum type="sha">3db38889a112ca99f2aa98d0c19d97a88d05626b</open-checksum>
  </data>
  <data type="filelists">
    <location href="repodata/filelists.xml.gz"/>
    <checksum type="sha">96a885e8225ad0ea3bc275cb681d778e1a8e7871</checksum>
    <timestamp>1253090753</timestamp>
    <open-checksum type="sha">bcde4210a59c1d2e781a04deb61ef90bae242f73</open-checksum>
  </data>
  <data type="primary">
    <location href="repodata/primary.xml.gz"/>
    <checksum type="sha">1f49334a5ea924f356092a2839d3a2db1b5cfd92</checksum>
    <timestamp>1253090753</timestamp>
    <open-checksum type="sha">80fe26640051a5e02e4e9683f04fd3b03941729d</open-checksum>
  </data>
</repomd>
