<?xml version="1.0" encoding="UTF-8"?>
<repomd xmlns="http://linux.duke.edu/metadata/repo">
  <data type="other">
    <location href="repodata/other.xml.gz"/>
    <checksum type="sha">d5c837ad7e68434805e66f2e86577f051736c0be</checksum>
    <timestamp>1264210104</timestamp>
    <open-checksum type="sha">a884a182fa64bd77ac115e2aa096bc8e88354c5d</open-checksum>
  </data>
  <data type="filelists">
    <location href="repodata/filelists.xml.gz"/>
    <checksum type="sha">d679318b64ffe179e028a12f23eacb3ed9542baf</checksum>
    <timestamp>1264210104</timestamp>
    <open-checksum type="sha">7b7e7252e3fa779c9472124471daba55d3200ad2</open-checksum>
  </data>
  <data type="primary">
    <location href="repodata/primary.xml.gz"/>
    <checksum type="sha">267f54ee0d1bdd09688228aad95dcbbae34822f6</checksum>
    <timestamp>1264210104</timestamp>
    <open-checksum type="sha">8998911f40585503229dd822f9cf7e1ab6d6f4ff</open-checksum>
  </data>
</repomd>
