<?xml version="1.0" encoding="UTF-8"?>
<repomd xmlns="http://linux.duke.edu/metadata/repo">
  <data type="other">
    <location href="repodata/other.xml.gz"/>
    <checksum type="sha">291b7c86a9a7e578e91a259ec2edd9fe15560fe2</checksum>
    <timestamp>1299123202</timestamp>
    <open-checksum type="sha">fc30b089cb19115ecaff5289a5301f1348b4c641</open-checksum>
  </data>
  <data type="filelists">
    <location href="repodata/filelists.xml.gz"/>
    <checksum type="sha">d34398af6156cab1226eb30b26647fbd38a75966</checksum>
    <timestamp>1299123202</timestamp>
    <open-checksum type="sha">e6216277d3c0d4be05ae08eb25d6abab55b7c6c7</open-checksum>
  </data>
  <data type="primary">
    <location href="repodata/primary.xml.gz"/>
    <checksum type="sha">3614350e4d4131d80a518ba3ca1553ee29e33c93</checksum>
    <timestamp>1299123202</timestamp>
    <open-checksum type="sha">6b1a4695a4d4b6dc3232691828748b4bdf323056</open-checksum>
  </data>
</repomd>
