<?xml version="1.0" encoding="UTF-8"?>
<repomd xmlns="http://linux.duke.edu/metadata/repo">
  <data type="other">
    <location href="repodata/other.xml.gz"/>
    <checksum type="sha">b9a81b1b75645f7ead4889ad1488e195cc96c47f</checksum>
    <timestamp>1352554213</timestamp>
    <open-checksum type="sha">58bb2e1bacb9f7e01b9d1d3a33587e092cbf9d32</open-checksum>
  </data>
  <data type="filelists">
    <location href="repodata/filelists.xml.gz"/>
    <checksum type="sha">2534cfda3a6933b8a04df3964bf15b8add975b9a</checksum>
    <timestamp>1352554213</timestamp>
    <open-checksum type="sha">f571fc5981cd2c97f1cbf2e0f167456d7bc7bed2</open-checksum>
  </data>
  <data type="primary">
    <location href="repodata/primary.xml.gz"/>
    <checksum type="sha">ce0ab41346c291f1d42952a11e9175295e2f2f54</checksum>
    <timestamp>1352554213</timestamp>
    <open-checksum type="sha">4d20ddc07dda98dafcc1d694bcd15b79e0f4f5db</open-checksum>
  </data>
</repomd>
