<?xml version="1.0" encoding="UTF-8"?>
<repomd xmlns="http://linux.duke.edu/metadata/repo">
  <data type="other">
    <location href="repodata/other.xml.gz"/>
    <checksum type="sha">9572943f3d9a33136d0106e1ca2888946eed7170</checksum>
    <timestamp>1320714996</timestamp>
    <open-checksum type="sha">c15f3dea9d57a102a70e78a588fc453258bbfc46</open-checksum>
  </data>
  <data type="filelists">
    <location href="repodata/filelists.xml.gz"/>
    <checksum type="sha">917ca2eacd996c97de4456bef6e1087697d03b9c</checksum>
    <timestamp>1320714996</timestamp>
    <open-checksum type="sha">fdcd23417aaf17acb9970d1994b293711c1ca20d</open-checksum>
  </data>
  <data type="primary">
    <location href="repodata/primary.xml.gz"/>
    <checksum type="sha">c94e8a47148b8e44c29d20ef4b76268adc04fa30</checksum>
    <timestamp>1320714996</timestamp>
    <open-checksum type="sha">58af932a183dd801f6d88786ae905c2e9fcd8f8f</open-checksum>
  </data>
</repomd>
