<?xml version="1.0" encoding="UTF-8"?>
<repomd xmlns="http://linux.duke.edu/metadata/repo">
  <data type="other">
    <location href="repodata/other.xml.gz"/>
    <checksum type="sha">7301ee64f5564cc882ed3b99af320cfe1c49ca77</checksum>
    <timestamp>1284080756</timestamp>
    <open-checksum type="sha">c7f21551198e04aff2db2b64282cd80aeae5678c</open-checksum>
  </data>
  <data type="filelists">
    <location href="repodata/filelists.xml.gz"/>
    <checksum type="sha">4d1803d82e2f25933eff1c5909c55ac705390811</checksum>
    <timestamp>1284080756</timestamp>
    <open-checksum type="sha">473d575ef134fd9db4d06c808891c465cfc78a89</open-checksum>
  </data>
  <data type="primary">
    <location href="repodata/primary.xml.gz"/>
    <checksum type="sha">43e37f86209bfbe97b0fd60c417c13f7472d5550</checksum>
    <timestamp>1284080756</timestamp>
    <open-checksum type="sha">e41dfc6165486d9b183875f7fee7666b527720cf</open-checksum>
  </data>
</repomd>
