<?xml version="1.0" encoding="UTF-8"?>
<repomd xmlns="http://linux.duke.edu/metadata/repo">
  <data type="other">
    <location href="repodata/other.xml.gz"/>
    <checksum type="sha">bf49d6dd5fefc472214ac1a64f3bf72494d7f3b7</checksum>
    <timestamp>1276564518</timestamp>
    <open-checksum type="sha">52fd6e1339fbc87240b5cb951b6becb289d20bef</open-checksum>
  </data>
  <data type="filelists">
    <location href="repodata/filelists.xml.gz"/>
    <checksum type="sha">68a6993052c3b5f15f0bbf40c48f2086555ba08e</checksum>
    <timestamp>1276564518</timestamp>
    <open-checksum type="sha">c34f241d72df9f47cd68e083c40a3eb1227eaa12</open-checksum>
  </data>
  <data type="primary">
    <location href="repodata/primary.xml.gz"/>
    <checksum type="sha">2c831ac12ac3568224b675f2331d710fe04910eb</checksum>
    <timestamp>1276564518</timestamp>
    <open-checksum type="sha">bf120d4a23efe0a2d96e50de07e4974ad55d7abe</open-checksum>
  </data>
</repomd>
