<?xml version="1.0" encoding="UTF-8"?>
<repomd xmlns="http://linux.duke.edu/metadata/repo">
  <data type="other">
    <location href="repodata/other.xml.gz"/>
    <checksum type="sha">00d7780cf690e086b2dd4edf42fdf96b552cb1f4</checksum>
    <timestamp>1317775162</timestamp>
    <open-checksum type="sha">8f5ea676baa03abf9b7bf09b67e0904a52859dd1</open-checksum>
  </data>
  <data type="filelists">
    <location href="repodata/filelists.xml.gz"/>
    <checksum type="sha">6e9a93242f887733e392187968b3a05021c3256c</checksum>
    <timestamp>1317775162</timestamp>
    <open-checksum type="sha">a427d739e82d18260d5ded4dd522d3d7dcdcb43d</open-checksum>
  </data>
  <data type="primary">
    <location href="repodata/primary.xml.gz"/>
    <checksum type="sha">eceb99cf4b2bb004b10b88a0776776a0dac9f302</checksum>
    <timestamp>1317775162</timestamp>
    <open-checksum type="sha">b7dab6fd1d35040710aabfbd0c8ab97b13b35af1</open-checksum>
  </data>
</repomd>
