<?xml version="1.0" encoding="UTF-8"?>
<repomd xmlns="http://linux.duke.edu/metadata/repo" xmlns:rpm="http://linux.duke.edu/metadata/rpm">
 <revision>1498368553</revision>
<data type="filelists">
  <checksum type="sha256">635767dc88e88ca5d6b4238566239292262dda5fc258d3b4be03802e5dc8e2ce</checksum>
  <open-checksum type="sha256">a2cb7432da9c9d9c6f5ab365eae5379bce97cf86152a13fdccc4a832eaf5d143</open-checksum>
  <location href="repodata/filelists.xml.gz"/>
  <timestamp>1498368554</timestamp>
  <size>79186</size>
  <open-size>1434075</open-size>
</data>
<data type="other">
  <checksum type="sha256">e5009fb5a95ba168069d3867da236ebc954df23fd51f464d3a5a0d46e5846cf6</checksum>
  <open-checksum type="sha256">1c43a834f656930217fd69fbfe30b8557badc758e43d1092dd6c7cabec5554f0</open-checksum>
  <location href="repodata/other.xml.gz"/>
  <timestamp>1498368554</timestamp>
  <size>3462</size>
  <open-size>19763</open-size>
</data>
<data type="primary">
  <checksum type="sha256">fda9f7a7c33f467c1f8350e1e61168b390533c7fe9b6a13a186666f043eb1f47</checksum>
  <open-checksum type="sha256">572d0415baf7cec1dc32c35831bbe8dbb8e8320e4e5dbf9e8c5049e37ba5cd68</open-checksum>
  <location href="repodata/primary.xml.gz"/>
  <timestamp>1498368554</timestamp>
  <size>160244</size>
  <open-size>1109151</open-size>
</data>
</repomd>
