<?xml version="1.0" encoding="UTF-8"?>
<repomd xmlns="http://linux.duke.edu/metadata/repo">
  <data type="other">
    <location href="repodata/other.xml.gz"/>
    <checksum type="sha">ae1687c80090da741be9f44d90845e3efb921244</checksum>
    <timestamp>1367061498</timestamp>
    <open-checksum type="sha">367845219c8c42215ae5a8eb6e4cc472bd17ad11</open-checksum>
  </data>
  <data type="filelists">
    <location href="repodata/filelists.xml.gz"/>
    <checksum type="sha">63eb49560a98f6585f758b2bdaaff41d1a8f2e70</checksum>
    <timestamp>1367061498</timestamp>
    <open-checksum type="sha">042027bc61c00e236331c6cf34d8af0876515b2b</open-checksum>
  </data>
  <data type="primary">
    <location href="repodata/primary.xml.gz"/>
    <checksum type="sha">33637362482985dcc50b0a23017da2aaff4afa43</checksum>
    <timestamp>1367061498</timestamp>
    <open-checksum type="sha">7d402ad020c80eb6da7f3496f5971e8b9b6c1bdd</open-checksum>
  </data>
</repomd>
